printmsg4pypi/__init__.py
printmsg4pypi/print_msg_file.py
printmsg4pypi-0.0.1.dist-info/METADATA
printmsg4pypi-0.0.1.dist-info/WHEEL
printmsg4pypi-0.0.1.dist-info/top_level.txt
printmsg4pypi-0.0.1.dist-info/RECORD
