Metadata-Version: 2.1
Name: printmsg4pypi
Version: 0.0.1
Summary: Test Package for Printing a Message
Home-page: UNKNOWN
Author: Mei-Chun Lo
Author-email: mcl@mail.shu.edu.tw
License: UNKNOWN
Platform: UNKNOWN
Requires-Python: >=3.6
